deeprank/__init__.py
deeprank/__version__.py
deeprank/config/__init__.py
deeprank/config/chemicals.py
deeprank/config/logger_settings.py
deeprank/features/AtomicFeature.py
deeprank/features/BSA.py
deeprank/features/FeatureClass.py
deeprank/features/FullPSSM.py
deeprank/features/PSSM_IC.py
deeprank/features/ResidueDensity.py
deeprank/features/__init__.py
deeprank/features/forcefield/patch.top
deeprank/features/forcefield/protein-allhdg5-4_new.param
deeprank/features/forcefield/protein-allhdg5-4_new.top
deeprank/generate/DataGenerator.py
deeprank/generate/GridTools.py
deeprank/generate/NormalizeData.py
deeprank/generate/__init__.py
deeprank/generate/kernel_map.c
deeprank/learn/DataSet.py
deeprank/learn/NeuralNet.py
deeprank/learn/__init__.py
deeprank/learn/classMetrics.py
deeprank/learn/metaqnn.py
deeprank/learn/model2d.py
deeprank/learn/model3d.py
deeprank/learn/modelGenerator.py
deeprank/learn/rankingMetrics.py
deeprank/targets/__init__.py
deeprank/targets/binary_class.py
deeprank/targets/capri_class.py
deeprank/targets/dockQ.py
deeprank/targets/rmsd_fnat.py
deeprank/tools/__init__.py
deeprank/tools/sasa.py
deeprank/tools/sparse.py
deeprank/utils/logger_helper.py
deeprank-0.2.1.dist-info/LICENSE
deeprank-0.2.1.dist-info/METADATA
deeprank-0.2.1.dist-info/NOTICE
deeprank-0.2.1.dist-info/WHEEL
deeprank-0.2.1.dist-info/top_level.txt
deeprank-0.2.1.dist-info/RECORD
