Metadata-Version: 2.1
Name: deeprank
Version: 0.2.1
Summary: Rank Protein-Protein Interactions using Deep Learning
Home-page: https://github.com/DeepRank/deeprank
Author: Nicolas Renaud, CunLiang Geng Sonja Georgrievska, Li Xue
License: Apache Software License 2.0
Project-URL: Source Code, https://github.com/DeepRank/deeprank
Project-URL: Documentation, https://deeprank.readthedocs.io
Project-URL: Issue tracker, https://github.com/DeepRank/deeprank/issues
Keywords: deeprank
Platform: UNKNOWN
Classifier: Development Status :: 3 - Alpha
Classifier: Intended Audience :: Science/Research
Classifier: License :: OSI Approved :: Apache Software License
Classifier: Natural Language :: English
Classifier: Programming Language :: Python :: 3.7
Classifier: Programming Language :: Python :: 3.8
Requires-Dist: numpy (>=1.13)
Requires-Dist: scipy
Requires-Dist: h5py
Requires-Dist: tqdm
Requires-Dist: pandas
Requires-Dist: mpi4py
Requires-Dist: matplotlib
Requires-Dist: torchsummary
Requires-Dist: torch
Requires-Dist: pdb2sql (>=0.5.0)
Requires-Dist: freesasa (==2.0.5) ; platform_system == "Darwin"
Requires-Dist: freesasa (==2.0.3.post7) ; platform_system == "Linux"
Provides-Extra: cuda
Requires-Dist: pycuda ; extra == 'cuda'
Provides-Extra: dev
Requires-Dist: prospector[with_pyroma] ; extra == 'dev'
Requires-Dist: autopep8 ; extra == 'dev'
Requires-Dist: isort ; extra == 'dev'
Provides-Extra: doc
Requires-Dist: sphinx ; extra == 'doc'
Provides-Extra: test
Requires-Dist: nose ; extra == 'test'
Requires-Dist: coverage ; extra == 'test'
Requires-Dist: pytest ; extra == 'test'
Requires-Dist: pytest-cov ; extra == 'test'
Requires-Dist: codacy-coverage ; extra == 'test'
Requires-Dist: coveralls ; extra == 'test'
